{
  "special-trains": [
    {
      "image": "Kalka-Shimla.jpg",
      "name": "Kalka Shimla Train",
      "source": "Kalka (KLK)",
      "destination": "Shimla (SML)",
      "date": "05-12-2026",
      "price": 550,
      "id": "1be3"
    },
    {
      "image": "baramula-jammu.jpg",
      "name": "Banihal - Baramula",
      "source": "Banihal",
      "destination": "Baramulla",
      "date": "12 Jan 2026",
      "price": 220,
      "id": "b722"
    },
    {
      "image": "munbai_goa.jpg",
      "name": "Mandovi Express",
      "source": "Nagpur",
      "destination": "Madgaon",
      "date": "20 Jul 2026",
      "price": 1450,
      "id": "74c6"
    },
    {
      "image": "jalpaiguri_darjeling.jpg",
      "name": "Darjeeling Train",
      "source": "New Jalpaiguri",
      "destination": "Darjeeling",
      "date": "28 Jul 2026",
      "price": 400,
      "id": "f0e3"
    },
    {
      "image": "Jaisalmer-to-Jodhpur.jpg",
      "name": "Jodhpur Express",
      "source": "Jaisalmer",
      "destination": "Jodhpur Junction",
      "date": "15 Feb 2026",
      "price": 650,
      "id": "3b74"
    }
  ],
  "search-history": [
    {
      "id": "f136",
      "from": "Bhopal",
      "to": "Raipur",
      "date": "2026-02-06",
      "loggedUser": null
    },
    {
      "id": "e851",
      "from": "Bhopal",
      "to": "Jaipur",
      "date": "2026-02-08",
      "loggedUser": null
    },
    {
      "id": "8edf",
      "from": "Kochi",
      "to": "Pune",
      "date": "2026-02-27",
      "loggedUser": null
    },
    {
      "id": "0e1a",
      "from": "Jaipur",
      "to": "Kolkata",
      "date": "2026-02-24",
      "loggedUser": null
    },
    {
      "id": "732f",
      "from": "Surat",
      "to": "Hyderabad",
      "date": "2026-02-27",
      "loggedUser": null
    },
    {
      "id": "3620",
      "from": "Surat",
      "to": "Hyderabad",
      "date": "2026-03-12",
      "loggedUser": null
    },
    {
      "id": "be51",
      "from": "Bhopal",
      "to": "Raipur",
      "date": "2026-02-19",
      "loggedUser": "taresh25202@gmail.com"
    }
  ],
  "train-route": [
    {
      "name": "Maharaja's Express",
      "source": "Delhi",
      "destination": "Lucknow",
      "date": "25 Apr 2026",
      "price": 125000,
      "id": "0bed"
    },
    {
      "name": "Palace on Wheels",
      "source": "Kanpur",
      "destination": "Agra",
      "date": "10 May 2026",
      "price": 98000,
      "id": "9c88"
    },
    {
      "name": "The Deccan Odyssey",
      "source": "Mumbai",
      "destination": "Nashik",
      "date": "18 Jun 2026",
      "price": 145000,
      "id": "23f3"
    }
  ],
  "smallroutes": [
    {
      "source": "Bhopal",
      "destination": "Raipur",
      "name": "Rajdhani Express",
      "price": 2200,
      "id": "079f"
    },
    {
      "source": "Kochi",
      "destination": "Pune",
      "name": "Deccan Queen",
      "price": 1800,
      "id": "3785"
    },
    {
      "source": "Bangalore",
      "destination": "Chennai",
      "name": "Shatabdi Express",
      "price": 1500,
      "id": "2ac5"
    },
    {
      "source": "Surat",
      "destination": "Hyderabad",
      "name": "Vande Bharat Express",
      "price": 2500,
      "id": "75b4"
    },
    {
      "source": "Jaipur",
      "destination": "Kolkata",
      "name": "Poorva Express",
      "price": 2000,
      "id": "b311"
    },
    {
      "source": "Vadodra",
      "destination": "Indore",
      "name": "Gareebrath Express",
      "price": 1600,
      "id": "1e3d"
    }
  ],
  "booking-data": [
    {
      "id": "e51e",
      "trainname": "Palace on Wheels",
      "passangername": "Harish",
      "numberofpassanger": "2",
      "fromstation": "Kanpur",
      "tostation": "Agra",
      "age": "29",
      "date": "2026-02-28",
      "gender": "Male",
      "coaches": "ACteir1"
    },
    {
      "id": "f51d",
      "trainname": "Maharaja's Express",
      "passangername": "Sanjay Yadav",
      "numberofpassanger": "3",
      "fromstation": "Delhi",
      "tostation": "Lucknow",
      "age": "22",
      "date": "2026-02-20",
      "gender": "Male",
      "coaches": "General"
    },
    {
      "id": "b826",
      "trainname": "Rajdhani Express",
      "passangername": "Krish Gour",
      "numberofpassanger": "5",
      "fromstation": "Bhopal",
      "tostation": "Raipur",
      "age": "25",
      "date": "2026-02-04",
      "gender": "Male"
    },
    {
      "id": "a93f",
      "trainname": "Darjeeling Train",
      "passangername": "Priyesh Mishra",
      "numberofpassanger": "4",
      "fromstation": "New Jalpaiguri",
      "tostation": "Darjeeling",
      "age": "25",
      "date": "2026-02-15",
      "gender": "Male",
      "coaches": "ACteir2"
    },
    {
      "id": "0736",
      "trainname": "Palace on Wheels",
      "passangername": "Aditya bankey",
      "numberofpassanger": "3",
      "fromstation": "Kanpur",
      "tostation": "Agra",
      "age": "35",
      "date": "2026-02-10",
      "gender": "Male",
      "coaches": "ACteir3"
    },
    {
      "id": "9c76",
      "trainname": "Shatabdi Express",
      "passangername": "Tanish Parihar",
      "numberofpassanger": "1",
      "fromstation": "Bangalore",
      "tostation": "Chennai",
      "age": "28",
      "date": "2026-03-07",
      "gender": "Male"
    },
    {
      "id": "1791",
      "trainname": "Jodhpur Express",
      "passangername": "Smriti Jaiswaal",
      "numberofpassanger": "10",
      "fromstation": "Jaisalmer",
      "tostation": "Jodhpur Junction",
      "age": "18",
      "date": "2026-03-02",
      "gender": "Female"
    },
    {
      "id": "0bda",
      "trainname": "Maharaja's Express",
      "passangername": "Taresh Tandy",
      "numberofpassanger": "2",
      "fromstation": "Delhi",
      "tostation": "Lucknow",
      "age": "20",
      "date": "2026-03-08",
      "gender": "Male",
      "price": 125000,
      "totalPrice": 250000,
      "coaches": "ACteir1"
    },
    {
      "id": "eb12",
      "trainname": "Poorva Express",
      "passangername": "Abhishek bharti",
      "numberofpassanger": "8",
      "fromstation": "Jaipur",
      "tostation": "Kolkata",
      "age": "19",
      "date": "2026-02-06",
      "gender": "Male",
      "price": 2000,
      "totalPrice": 16000
    },
    {
      "id": "8f46",
      "trainname": "Vande Bharat Express",
      "passangername": "Tanmay bhai",
      "numberofpassanger": "10",
      "fromstation": "Surat",
      "tostation": "Hyderabad",
      "age": "28",
      "date": "2026-03-02",
      "gender": "Male",
      "price": 2500,
      "totalPrice": 25000,
      "coaches": "General"
    },
    {
      "id": "4f39",
      "trainname": "Deccan Queen",
      "passangername": "Aditya bankey",
      "numberofpassanger": "2",
      "fromstation": "Kochi",
      "tostation": "Pune",
      "age": "25",
      "date": "2026-02-14",
      "gender": "Male",
      "price": 1800,
      "totalPrice": 3600,
      "userEmail": "a@gmail.com",
      "loggedUser": "a@gmail.com"
    },
    {
      "id": "d4b4",
      "trainname": "Maharaja's Express",
      "passangername": "Taresh Tandy",
      "numberofpassanger": "2",
      "fromstation": "Delhi",
      "tostation": "Lucknow",
      "age": "20",
      "date": "2026-02-07",
      "gender": "Male",
      "coach": "ACteir1",
      "price": 125000,
      "totalPrice": 250000,
      "userEmail": "taresh25202@gmail.com",
      "loggedUser": "taresh25202@gmail.com"
    },
    {
      "id": "d375",
      "trainname": "Mandovi Express",
      "passangername": "Aditya bankey",
      "numberofpassanger": "5",
      "fromstation": "Nagpur",
      "tostation": "Madgaon",
      "age": "25",
      "date": "2026-02-18",
      "gender": "Male",
      "coach": "Sleeper",
      "price": 1450,
      "totalPrice": 7250,
      "userEmail": "taresh25202@gmail.com",
      "loggedUser": "taresh25202@gmail.com"
    },
    {
      "id": "471a",
      "trainname": "Jodhpur Express",
      "passangername": "Smriti Jaiswaal",
      "numberofpassanger": "3",
      "fromstation": "Jaisalmer",
      "tostation": "Jodhpur Junction",
      "age": "19",
      "date": "2026-02-10",
      "gender": "Female",
      "coach": "General",
      "price": 650,
      "totalPrice": 1950,
      "userEmail": "taresh25202@gmail.com",
      "loggedUser": "taresh25202@gmail.com"
    },
    {
      "id": "df11",
      "trainname": "Vande Bharat Express",
      "passangername": "Priyesh Mishra",
      "numberofpassanger": "10",
      "fromstation": "Surat",
      "tostation": "Hyderabad",
      "age": "28",
      "date": "2026-02-22",
      "gender": "Male",
      "coach": "ACteir3",
      "price": 2500,
      "totalPrice": 25000,
      "userEmail": "taresh25202@gmail.com",
      "loggedUser": "taresh25202@gmail.com"
    },
    {
      "id": "803a",
      "trainname": "Poorva Express",
      "passangername": "Tanish Parihar",
      "numberofpassanger": "4",
      "fromstation": "Jaipur",
      "tostation": "Kolkata",
      "age": "23",
      "date": "2026-02-17",
      "gender": "Male",
      "coach": "ACteir2",
      "price": 2000,
      "totalPrice": 8000,
      "userEmail": "taresh25202@gmail.com",
      "loggedUser": "taresh25202@gmail.com"
    },
    {
      "id": "73a3",
      "trainname": "Gareebrath Express",
      "passangername": "Siddharth israni",
      "numberofpassanger": "1",
      "fromstation": "Vadodra",
      "tostation": "Indore",
      "age": "26",
      "date": "2026-03-07",
      "gender": "Male",
      "coach": "General",
      "price": 1600,
      "totalPrice": 1600,
      "userEmail": "taresh25202@gmail.com",
      "loggedUser": "taresh25202@gmail.com"
    },
    {
      "id": "bd55",
      "trainname": "Deccan Queen",
      "passangername": "Krish Gour",
      "numberofpassanger": "6",
      "fromstation": "Kochi",
      "tostation": "Pune",
      "age": "18",
      "date": "2026-02-07",
      "gender": "Male",
      "coach": "Sleeper",
      "price": 1800,
      "totalPrice": 10800,
      "userEmail": "taresh25202@gmail.com",
      "loggedUser": "taresh25202@gmail.com"
    }
  ]
}